odoo/addons/stock_picking_terms/README.rst
odoo/addons/stock_picking_terms/__init__.py
odoo/addons/stock_picking_terms/__manifest__.py
odoo/addons/stock_picking_terms/i18n/es.po
odoo/addons/stock_picking_terms/models/__init__.py
odoo/addons/stock_picking_terms/models/company.py
odoo/addons/stock_picking_terms/models/res_config_settings.py
odoo/addons/stock_picking_terms/models/stock_picking.py
odoo/addons/stock_picking_terms/reports/report_deliveryslip.xml
odoo/addons/stock_picking_terms/static/description/icon.png
odoo/addons/stock_picking_terms/views/res_config_settings_views.xml
odoo/addons/stock_picking_terms/views/stock_picking_type_views.xml
odoo/addons/stock_picking_terms/views/stock_picking_views.xml
odoo_addon_stock_picking_terms-16.0.1.0.0.1.dist-info/METADATA
odoo_addon_stock_picking_terms-16.0.1.0.0.1.dist-info/WHEEL
odoo_addon_stock_picking_terms-16.0.1.0.0.1.dist-info/top_level.txt
odoo_addon_stock_picking_terms-16.0.1.0.0.1.dist-info/RECORD
